easymoe-0.1.0.dist-info/licenses/LICENSE
my_package/__init__.py
my_package/main.py
easymoe-0.1.0.dist-info/METADATA
easymoe-0.1.0.dist-info/WHEEL
easymoe-0.1.0.dist-info/top_level.txt
easymoe-0.1.0.dist-info/RECORD
