Metadata-Version: 2.4
Name: easymoe
Version: 0.1.0
Summary: easymoe v1.0.0
Author: Author
Author-email: sangyoon <oogleg600@gmail.com>
License: MIT
Project-URL: Homepage, https://pypi.org/project/easymoe/
Requires-Python: >=3.8
License-File: LICENSE
Dynamic: license-file
